forecast_x/__init__.py
forecast_x/forecast_x.py
forecast_x-0.12.20.dist-info/LICENSE
forecast_x-0.12.20.dist-info/METADATA
forecast_x-0.12.20.dist-info/WHEEL
forecast_x-0.12.20.dist-info/top_level.txt
forecast_x-0.12.20.dist-info/RECORD
