Metadata-Version: 2.1
Name: forecast-x
Version: 0.12.20
Summary: Forecasting Model package based on naive models
Home-page: https://github.com/alejandrodbn/forecast
Author: Alejandro De Barros
Author-email: alejandrodbn@gmail.com
License: UNKNOWN
Platform: UNKNOWN
Classifier: Programming Language :: Python :: 3.6
Classifier: Programming Language :: Python :: 3.7
Classifier: Development Status :: 4 - Beta
Classifier: License :: OSI Approved :: MIT License
Classifier: Operating System :: OS Independent
